{
    "attributes": [],
    "class": "ShaderNodeHairInfo",
    "inputs": [],
    "label": "Curves Info",
    "outputs": [
        {
            "class": "NodeSocketFloat",
            "identifier": "Is Strand",
            "index": 0,
            "name": "Is Strand"
        },
        {
            "class": "NodeSocketFloat",
            "identifier": "Intercept",
            "index": 1,
            "name": "Intercept"
        },
        {
            "class": "NodeSocketFloat",
            "identifier": "Length",
            "index": 2,
            "name": "Length"
        },
        {
            "class": "NodeSocketFloat",
            "identifier": "Thickness",
            "index": 3,
            "name": "Thickness"
        },
        {
            "class": "NodeSocketVector",
            "identifier": "Tangent Normal",
            "index": 4,
            "name": "Tangent Normal"
        },
        {
            "class": "NodeSocketFloat",
            "identifier": "Random",
            "index": 5,
            "name": "Random"
        }
    ]
}